CHANGES.md
INSTALL.md
MANIFEST.in
README.md
pyproject.toml
setup.py
custom_cryptofeed/__init__.py
custom_cryptofeed/callback.py
custom_cryptofeed/config.py
custom_cryptofeed/connection.py
custom_cryptofeed/connection_handler.py
custom_cryptofeed/defines.py
custom_cryptofeed/exceptions.py
custom_cryptofeed/exchange.py
custom_cryptofeed/feed.py
custom_cryptofeed/feedhandler.py
custom_cryptofeed/log.py
custom_cryptofeed/nbbo.py
custom_cryptofeed/raw_data_collection.py
custom_cryptofeed/symbols.py
custom_cryptofeed/types.c
custom_cryptofeed/types.pyx
custom_cryptofeed.egg-info/PKG-INFO
custom_cryptofeed.egg-info/SOURCES.txt
custom_cryptofeed.egg-info/dependency_links.txt
custom_cryptofeed.egg-info/requires.txt
custom_cryptofeed.egg-info/top_level.txt
custom_cryptofeed/backends/__init__.py
custom_cryptofeed/backends/_util.py
custom_cryptofeed/backends/aggregate.py
custom_cryptofeed/backends/arctic.py
custom_cryptofeed/backends/backend.py
custom_cryptofeed/backends/gcppubsub.py
custom_cryptofeed/backends/http.py
custom_cryptofeed/backends/influxdb.py
custom_cryptofeed/backends/kafka.py
custom_cryptofeed/backends/mongo.py
custom_cryptofeed/backends/postgres.py
custom_cryptofeed/backends/quest.py
custom_cryptofeed/backends/rabbitmq.py
custom_cryptofeed/backends/redis.py
custom_cryptofeed/backends/socket.py
custom_cryptofeed/backends/zmq.py
custom_cryptofeed/exchanges/__init__.py
custom_cryptofeed/exchanges/ascendex.py
custom_cryptofeed/exchanges/ascendex_futures.py
custom_cryptofeed/exchanges/bequant.py
custom_cryptofeed/exchanges/binance.py
custom_cryptofeed/exchanges/binance_delivery.py
custom_cryptofeed/exchanges/binance_futures.py
custom_cryptofeed/exchanges/binance_us.py
custom_cryptofeed/exchanges/bitdotcom.py
custom_cryptofeed/exchanges/bitfinex.py
custom_cryptofeed/exchanges/bitflyer.py
custom_cryptofeed/exchanges/bitget.py
custom_cryptofeed/exchanges/bithumb.py
custom_cryptofeed/exchanges/bitmex.py
custom_cryptofeed/exchanges/bitstamp.py
custom_cryptofeed/exchanges/bittrex.py
custom_cryptofeed/exchanges/blockchain.py
custom_cryptofeed/exchanges/bybit.py
custom_cryptofeed/exchanges/coinbase.py
custom_cryptofeed/exchanges/cryptodotcom.py
